<changeset id="55512803" schema="1"><counts nodesAdded="106" nodesModified="4" relationsAdded="0" relationsModified="0" waysAdded="13" waysModified="4" /><meta><tag k="changesets_count" v="4677" /><tag k="comment" v="to improve map" /><tag k="created_by" v="iD 2.5.1" /><tag k="host" v="https://www.openstreetmap.org/edit" /><tag k="imagery_used" v="Bing aerial imagery" /><tag k="locale" v="en-US" /></meta><body><tag id="553682825" k="highway" o="add" type="way" v="track" /><tag id="553682826" k="highway" o="add" type="way" v="track" /><tag id="553682827" k="highway" o="add" type="way" v="track" /><tag id="553682828" k="highway" o="add" type="way" v="track" /><tag id="553682829" k="highway" o="add" type="way" v="track" /><tag id="553682830" k="highway" o="add" type="way" v="track" /><tag id="553682831" k="highway" o="add" type="way" v="track" /><tag id="553682832" k="highway" o="add" type="way" v="track" /><tag id="553682833" k="highway" o="add" type="way" v="track" /><tag id="553682834" k="highway" o="add" type="way" v="track" /><tag id="553682835" k="highway" o="add" type="way" v="track" /><tag id="553682836" k="highway" o="add" type="way" v="track" /><tag id="553682837" k="highway" o="add" type="way" v="track" /><tag id="553617235" k="highway" o="add" type="way" v="track" /></body></changeset>