<changeset id="7762091" schema="2">
  <counts nodesAdded="34" nodesDeleted="0" nodesModified="1" relationsAdded="0" relationsDeleted="0" relationsModified="0" waysAdded="2" waysDeleted="0" waysModified="6" />
  <meta>
    <tag k="comment" v="1100404&#51061;&#49328;" />
    <tag k="created_by" v="JOSM/1.5 (3966 en)" />
  </meta>
  <body>
    <tag id="1232013082" k="name" o="add" type="node" v="&#51008;&#54665;&#45208;&#47924;" />
    <tag id="1232013082" k="natural" o="add" type="node" v="tree" />
    <tag id="107159849" k="highway" o="add" type="way" v="pedestrian" />
    <tag id="368635911" k="historic" o="none" type="node" v="monument" />
    <tag id="368635911" k="name" o="none" type="node" v="&#46041;&#54617;&#54785;&#47749;&#44592;&#45392;&#44288; (Donghakhyeongmyeong Memorial Hall)" />
    <tag id="368635911" k="name:en" o="none" type="node" v="Donghakhyeongmyeong Memorial Hall" />
    <tag id="368635911" k="name:ko_rm" o="none" type="node" v="Donghakhyeongmyeongginyeomgwan" />
    <tag id="368635911" k="ncat" o="none" type="node" v="&#44592;&#45392;&#44288;" />
    <tag id="368635911" k="source" o="none" type="node" v="http://kr.open.gugi.yahoo.com" />
    <tag id="368635911" k="tourism" o="none" type="node" v="museum" />
    <tag id="37973895" k="highway" o="none" type="way" v="residential" />
    <tag id="37973895" k="name" o="none" type="way" v="Nosong01" />
    <tag id="36837141" k="highway" o="none" type="way" v="residential" />
    <tag id="36837141" k="name" o="none" type="way" v="Ajung" />
    <tag id="75507898" k="highway" o="modify" type="way" v="pedestrian" />
    <tag id="36962470" k="highway" o="none" type="way" v="unclassified" />
    <tag id="34383845" k="highway" o="none" type="way" v="unclassified" />
  </body>
</changeset>
