<changeset id="43817219" schema="2">
  <counts nodesAdded="159" nodesDeleted="0" nodesModified="0" relationsAdded="0" relationsDeleted="0" relationsModified="0" waysAdded="40" waysDeleted="0" waysModified="0" />
  <meta>
    <tag k="comment" v="Use Bing imagery to improve detail around Monkseaton" />
    <tag k="created_by" v="JOSM/1.5 (11283 en_GB)" />
    <tag k="source" v="Bing; local knowledge" />
  </meta>
  <body>
    <tag id="454624242" k="source" o="add" type="way" v="Bing" />
    <tag id="454624242" k="barrier" o="add" type="way" v="fence" />
    <tag id="454624243" k="source" o="add" type="way" v="Bing" />
    <tag id="454624243" k="building" o="add" type="way" v="residential" />
    <tag id="454624244" k="source" o="add" type="way" v="Bing" />
    <tag id="454624244" k="building" o="add" type="way" v="residential" />
    <tag id="454624245" k="source" o="add" type="way" v="Bing" />
    <tag id="454624245" k="building" o="add" type="way" v="residential" />
    <tag id="454624246" k="source" o="add" type="way" v="Bing" />
    <tag id="454624246" k="building" o="add" type="way" v="residential" />
    <tag id="454624247" k="source" o="add" type="way" v="Bing" />
    <tag id="454624247" k="building" o="add" type="way" v="residential" />
    <tag id="454624248" k="source" o="add" type="way" v="Bing" />
    <tag id="454624248" k="building" o="add" type="way" v="residential" />
    <tag id="454624250" k="source" o="add" type="way" v="Bing" />
    <tag id="454624250" k="building" o="add" type="way" v="residential" />
    <tag id="454624251" k="source" o="add" type="way" v="Bing" />
    <tag id="454624251" k="building" o="add" type="way" v="residential" />
    <tag id="454624252" k="source" o="add" type="way" v="Bing" />
    <tag id="454624252" k="barrier" o="add" type="way" v="fence" />
    <tag id="454624253" k="source" o="add" type="way" v="Bing" />
    <tag id="454624253" k="barrier" o="add" type="way" v="fence" />
    <tag id="454624254" k="source" o="add" type="way" v="Bing" />
    <tag id="454624254" k="building" o="add" type="way" v="residential" />
    <tag id="454624255" k="source" o="add" type="way" v="Bing" />
    <tag id="454624255" k="building" o="add" type="way" v="residential" />
    <tag id="454624256" k="source" o="add" type="way" v="Bing" />
    <tag id="454624256" k="building" o="add" type="way" v="residential" />
    <tag id="454624257" k="source" o="add" type="way" v="Bing" />
    <tag id="454624257" k="building" o="add" type="way" v="residential" />
    <tag id="454624259" k="source" o="add" type="way" v="Bing" />
    <tag id="454624259" k="building" o="add" type="way" v="residential" />
    <tag id="454624260" k="source" o="add" type="way" v="Bing" />
    <tag id="454624260" k="building" o="add" type="way" v="residential" />
    <tag id="454624261" k="source" o="add" type="way" v="Bing" />
    <tag id="454624261" k="building" o="add" type="way" v="residential" />
    <tag id="454624262" k="source" o="add" type="way" v="Bing" />
    <tag id="454624262" k="building" o="add" type="way" v="residential" />
    <tag id="454624263" k="source" o="add" type="way" v="Bing" />
    <tag id="454624263" k="building" o="add" type="way" v="residential" />
    <tag id="454624264" k="source" o="add" type="way" v="Bing" />
    <tag id="454624264" k="building" o="add" type="way" v="residential" />
    <tag id="454624265" k="source" o="add" type="way" v="Bing" />
    <tag id="454624265" k="building" o="add" type="way" v="residential" />
    <tag id="454624266" k="source" o="add" type="way" v="Bing" />
    <tag id="454624266" k="building" o="add" type="way" v="residential" />
    <tag id="454624269" k="source" o="add" type="way" v="Bing" />
    <tag id="454624269" k="building" o="add" type="way" v="residential" />
    <tag id="454624270" k="source" o="add" type="way" v="Bing" />
    <tag id="454624270" k="building" o="add" type="way" v="residential" />
    <tag id="454624271" k="source" o="add" type="way" v="Bing" />
    <tag id="454624271" k="building" o="add" type="way" v="residential" />
    <tag id="454624272" k="source" o="add" type="way" v="Bing" />
    <tag id="454624272" k="building" o="add" type="way" v="residential" />
    <tag id="454624273" k="source" o="add" type="way" v="Bing" />
    <tag id="454624273" k="building" o="add" type="way" v="residential" />
    <tag id="454624274" k="source" o="add" type="way" v="Bing" />
    <tag id="454624274" k="building" o="add" type="way" v="residential" />
    <tag id="454624275" k="source" o="add" type="way" v="Bing" />
    <tag id="454624275" k="building" o="add" type="way" v="residential" />
    <tag id="454624276" k="source" o="add" type="way" v="Bing" />
    <tag id="454624276" k="building" o="add" type="way" v="residential" />
    <tag id="454624277" k="source" o="add" type="way" v="Bing" />
    <tag id="454624277" k="building" o="add" type="way" v="residential" />
    <tag id="454624279" k="source" o="add" type="way" v="Bing" />
    <tag id="454624279" k="building" o="add" type="way" v="residential" />
    <tag id="454624280" k="source" o="add" type="way" v="Bing" />
    <tag id="454624280" k="building" o="add" type="way" v="residential" />
    <tag id="454624281" k="source" o="add" type="way" v="Bing" />
    <tag id="454624281" k="building" o="add" type="way" v="residential" />
    <tag id="454624282" k="source" o="add" type="way" v="Bing" />
    <tag id="454624282" k="building" o="add" type="way" v="residential" />
    <tag id="454624283" k="source" o="add" type="way" v="Bing" />
    <tag id="454624283" k="building" o="add" type="way" v="residential" />
    <tag id="454624284" k="source" o="add" type="way" v="Bing" />
    <tag id="454624284" k="building" o="add" type="way" v="residential" />
    <tag id="454624285" k="source" o="add" type="way" v="Bing" />
    <tag id="454624285" k="building" o="add" type="way" v="residential" />
    <tag id="454624286" k="source" o="add" type="way" v="Bing" />
    <tag id="454624286" k="building" o="add" type="way" v="residential" />
  </body>
</changeset>
