<changeset id="43720322" schema="2">
  <counts nodesAdded="1008" nodesDeleted="0" nodesModified="0" relationsAdded="0" relationsDeleted="0" relationsModified="0" waysAdded="449" waysDeleted="0" waysModified="0" />
  <meta>
    <tag k="comment" v="#ProjectNOAH-ISAIAH #hotosm-project-1886" />
    <tag k="created_by" v="JOSM/1.5 (10966 en)" />
    <tag k="source" v="Bing" />
  </meta>
  <body>
    <tag id="453911669" k="Province" o="add" type="way" v="Batangas" />
    <tag id="453911669" k="building" o="add" type="way" v="yes" />
    <tag id="453911670" k="Province" o="add" type="way" v="Batangas" />
    <tag id="453911670" k="building" o="add" type="way" v="yes" />
    <tag id="453911671" k="Province" o="add" type="way" v="Batangas" />
    <tag id="453911671" k="building" o="add" type="way" v="yes" />
    <tag id="453911672" k="Province" o="add" type="way" v="Batangas" />
    <tag id="453911672" k="building" o="add" type="way" v="yes" />
    <tag id="453911673" k="Province" o="add" type="way" v="Batangas" />
    <tag id="453911673" k="building" o="add" type="way" v="yes" />
    <tag id="453911674" k="Province" o="add" type="way" v="Batangas" />
    <tag id="453911674" k="building" o="add" type="way" v="yes" />
    <tag id="453911675" k="Province" o="add" type="way" v="Batangas" />
    <tag id="453911675" k="building" o="add" type="way" v="yes" />
    <tag id="453911676" k="Province" o="add" type="way" v="Batangas" />
    <tag id="453911676" k="building" o="add" type="way" v="yes" />
    <tag id="453911677" k="Province" o="add" type="way" v="Batangas" />
    <tag id="453911677" k="building" o="add" type="way" v="yes" />
    <tag id="453911678" k="Province" o="add" type="way" v="Batangas" />
    <tag id="453911678" k="building" o="add" type="way" v="yes" />
    <tag id="453911679" k="Province" o="add" type="way" v="Batangas" />
    <tag id="453911679" k="building" o="add" type="way" v="yes" />
    <tag id="453911680" k="Province" o="add" type="way" v="Batangas" />
    <tag id="453911680" k="building" o="add" type="way" v="yes" />
    <tag id="453911681" k="Province" o="add" type="way" v="Batangas" />
    <tag id="453911681" k="building" o="add" type="way" v="yes" />
    <tag id="453911683" k="Province" o="add" type="way" v="Batangas" />
    <tag id="453911683" k="building" o="add" type="way" v="yes" />
    <tag id="453911684" k="Province" o="add" type="way" v="Batangas" />
    <tag id="453911684" k="building" o="add" type="way" v="yes" />
    <tag id="453911685" k="Province" o="add" type="way" v="Batangas" />
    <tag id="453911685" k="building" o="add" type="way" v="yes" />
    <tag id="453911687" k="Province" o="add" type="way" v="Batangas" />
    <tag id="453911687" k="building" o="add" type="way" v="yes" />
    <tag id="453911688" k="Province" o="add" type="way" v="Batangas" />
    <tag id="453911688" k="building" o="add" type="way" v="yes" />
    <tag id="453911689" k="Province" o="add" type="way" v="Batangas" />
    <tag id="453911689" k="building" o="add" type="way" v="yes" />
    <tag id="453911690" k="Province" o="add" type="way" v="Batangas" />
    <tag id="453911690" k="building" o="add" type="way" v="yes" />
    <tag id="453911691" k="Province" o="add" type="way" v="Batangas" />
    <tag id="453911691" k="building" o="add" type="way" v="yes" />
    <tag id="453911692" k="Province" o="add" type="way" v="Batangas" />
    <tag id="453911692" k="building" o="add" type="way" v="yes" />
    <tag id="453911693" k="Province" o="add" type="way" v="Batangas" />
    <tag id="453911693" k="building" o="add" type="way" v="yes" />
    <tag id="453911694" k="Province" o="add" type="way" v="Batangas" />
    <tag id="453911694" k="building" o="add" type="way" v="yes" />
    <tag id="453911695" k="Province" o="add" type="way" v="Batangas" />
    <tag id="453911695" k="building" o="add" type="way" v="yes" />
    <tag id="453911696" k="Province" o="add" type="way" v="Batangas" />
    <tag id="453911696" k="building" o="add" type="way" v="yes" />
    <tag id="453911697" k="Province" o="add" type="way" v="Batangas" />
    <tag id="453911697" k="building" o="add" type="way" v="yes" />
    <tag id="453911698" k="Province" o="add" type="way" v="Batangas" />
    <tag id="453911698" k="building" o="add" type="way" v="yes" />
    <tag id="453911699" k="Province" o="add" type="way" v="Batangas" />
    <tag id="453911699" k="building" o="add" type="way" v="yes" />
    <tag id="453911700" k="Province" o="add" type="way" v="Batangas" />
    <tag id="453911700" k="building" o="add" type="way" v="yes" />
    <tag id="453911701" k="Province" o="add" type="way" v="Batangas" />
    <tag id="453911701" k="building" o="add" type="way" v="yes" />
    <tag id="453911702" k="Province" o="add" type="way" v="Batangas" />
    <tag id="453911702" k="building" o="add" type="way" v="yes" />
    <tag id="453911703" k="Province" o="add" type="way" v="Batangas" />
    <tag id="453911703" k="building" o="add" type="way" v="yes" />
    <tag id="453911704" k="Province" o="add" type="way" v="Batangas" />
    <tag id="453911704" k="building" o="add" type="way" v="yes" />
    <tag id="453911705" k="Province" o="add" type="way" v="Batangas" />
    <tag id="453911705" k="building" o="add" type="way" v="yes" />
    <tag id="453911706" k="Province" o="add" type="way" v="Batangas" />
    <tag id="453911706" k="building" o="add" type="way" v="yes" />
    <tag id="453911707" k="Province" o="add" type="way" v="Batangas" />
    <tag id="453911707" k="building" o="add" type="way" v="yes" />
    <tag id="453911708" k="Province" o="add" type="way" v="Batangas" />
    <tag id="453911708" k="building" o="add" type="way" v="yes" />
    <tag id="453911709" k="Province" o="add" type="way" v="Batangas" />
    <tag id="453911709" k="building" o="add" type="way" v="yes" />
    <tag id="453911710" k="Province" o="add" type="way" v="Batangas" />
    <tag id="453911710" k="building" o="add" type="way" v="yes" />
    <tag id="453911711" k="Province" o="add" type="way" v="Batangas" />
    <tag id="453911711" k="building" o="add" type="way" v="yes" />
    <tag id="453911712" k="Province" o="add" type="way" v="Batangas" />
    <tag id="453911712" k="building" o="add" type="way" v="yes" />
    <tag id="453911713" k="Province" o="add" type="way" v="Batangas" />
    <tag id="453911713" k="building" o="add" type="way" v="yes" />
    <tag id="453911714" k="Province" o="add" type="way" v="Batangas" />
    <tag id="453911714" k="building" o="add" type="way" v="yes" />
    <tag id="453911715" k="Province" o="add" type="way" v="Batangas" />
    <tag id="453911715" k="building" o="add" type="way" v="yes" />
    <tag id="453911716" k="Province" o="add" type="way" v="Batangas" />
    <tag id="453911716" k="building" o="add" type="way" v="yes" />
    <tag id="453911717" k="Province" o="add" type="way" v="Batangas" />
    <tag id="453911717" k="building" o="add" type="way" v="yes" />
    <tag id="453911718" k="Province" o="add" type="way" v="Batangas" />
    <tag id="453911718" k="building" o="add" type="way" v="yes" />
    <tag id="453911719" k="Province" o="add" type="way" v="Batangas" />
    <tag id="453911719" k="building" o="add" type="way" v="yes" />
    <tag id="453911720" k="Province" o="add" type="way" v="Batangas" />
    <tag id="453911720" k="building" o="add" type="way" v="yes" />
    <tag id="453911721" k="Province" o="add" type="way" v="Batangas" />
    <tag id="453911721" k="building" o="add" type="way" v="yes" />
    <tag id="453911722" k="Province" o="add" type="way" v="Batangas" />
    <tag id="453911722" k="building" o="add" type="way" v="yes" />
    <tag id="453911723" k="Province" o="add" type="way" v="Batangas" />
    <tag id="453911723" k="building" o="add" type="way" v="yes" />
    <tag id="453911724" k="Province" o="add" type="way" v="Batangas" />
    <tag id="453911724" k="building" o="add" type="way" v="yes" />
    <tag id="453911725" k="Province" o="add" type="way" v="Batangas" />
    <tag id="453911725" k="building" o="add" type="way" v="yes" />
    <tag id="453911726" k="Province" o="add" type="way" v="Batangas" />
    <tag id="453911726" k="building" o="add" type="way" v="yes" />
    <tag id="453911727" k="Province" o="add" type="way" v="Batangas" />
    <tag id="453911727" k="building" o="add" type="way" v="yes" />
    <tag id="453911728" k="Province" o="add" type="way" v="Batangas" />
    <tag id="453911728" k="building" o="add" type="way" v="yes" />
    <tag id="453911729" k="Province" o="add" type="way" v="Batangas" />
    <tag id="453911729" k="building" o="add" type="way" v="yes" />
    <tag id="453911730" k="Province" o="add" type="way" v="Batangas" />
    <tag id="453911730" k="building" o="add" type="way" v="yes" />
    <tag id="453911731" k="Province" o="add" type="way" v="Batangas" />
    <tag id="453911731" k="building" o="add" type="way" v="yes" />
    <tag id="453911732" k="Province" o="add" type="way" v="Batangas" />
    <tag id="453911732" k="building" o="add" type="way" v="yes" />
    <tag id="453911733" k="Province" o="add" type="way" v="Batangas" />
    <tag id="453911733" k="building" o="add" type="way" v="yes" />
    <tag id="453911734" k="Province" o="add" type="way" v="Batangas" />
    <tag id="453911734" k="building" o="add" type="way" v="yes" />
    <tag id="453911735" k="Province" o="add" type="way" v="Batangas" />
    <tag id="453911735" k="building" o="add" type="way" v="yes" />
    <tag id="453911736" k="Province" o="add" type="way" v="Batangas" />
    <tag id="453911736" k="building" o="add" type="way" v="yes" />
    <tag id="453911737" k="Province" o="add" type="way" v="Batangas" />
    <tag id="453911737" k="building" o="add" type="way" v="yes" />
    <tag id="453911738" k="Province" o="add" type="way" v="Batangas" />
    <tag id="453911738" k="building" o="add" type="way" v="yes" />
    <tag id="453911739" k="Province" o="add" type="way" v="Batangas" />
    <tag id="453911739" k="building" o="add" type="way" v="yes" />
    <tag id="453911740" k="Province" o="add" type="way" v="Batangas" />
    <tag id="453911740" k="building" o="add" type="way" v="yes" />
    <tag id="453911741" k="Province" o="add" type="way" v="Batangas" />
    <tag id="453911741" k="building" o="add" type="way" v="yes" />
    <tag id="453911742" k="Province" o="add" type="way" v="Batangas" />
    <tag id="453911742" k="building" o="add" type="way" v="yes" />
    <tag id="453911743" k="Province" o="add" type="way" v="Batangas" />
    <tag id="453911743" k="building" o="add" type="way" v="yes" />
    <tag id="453911744" k="Province" o="add" type="way" v="Batangas" />
    <tag id="453911744" k="building" o="add" type="way" v="yes" />
    <tag id="453911745" k="Province" o="add" type="way" v="Batangas" />
    <tag id="453911745" k="building" o="add" type="way" v="yes" />
    <tag id="453911746" k="Province" o="add" type="way" v="Batangas" />
    <tag id="453911746" k="building" o="add" type="way" v="yes" />
    <tag id="453911747" k="Province" o="add" type="way" v="Batangas" />
    <tag id="453911747" k="building" o="add" type="way" v="yes" />
    <tag id="453911748" k="Province" o="add" type="way" v="Batangas" />
    <tag id="453911748" k="building" o="add" type="way" v="yes" />
    <tag id="453911749" k="Province" o="add" type="way" v="Batangas" />
    <tag id="453911749" k="building" o="add" type="way" v="yes" />
    <tag id="453911750" k="Province" o="add" type="way" v="Batangas" />
    <tag id="453911750" k="building" o="add" type="way" v="yes" />
    <tag id="453911751" k="Province" o="add" type="way" v="Batangas" />
    <tag id="453911751" k="building" o="add" type="way" v="yes" />
    <tag id="453911752" k="Province" o="add" type="way" v="Batangas" />
    <tag id="453911752" k="building" o="add" type="way" v="yes" />
    <tag id="453911753" k="Province" o="add" type="way" v="Batangas" />
    <tag id="453911753" k="building" o="add" type="way" v="yes" />
    <tag id="453911754" k="Province" o="add" type="way" v="Batangas" />
    <tag id="453911754" k="building" o="add" type="way" v="yes" />
    <tag id="453911755" k="Province" o="add" type="way" v="Batangas" />
    <tag id="453911755" k="building" o="add" type="way" v="yes" />
    <tag id="453911756" k="Province" o="add" type="way" v="Batangas" />
    <tag id="453911756" k="building" o="add" type="way" v="yes" />
    <tag id="453911757" k="Province" o="add" type="way" v="Batangas" />
    <tag id="453911757" k="building" o="add" type="way" v="yes" />
    <tag id="453911758" k="Province" o="add" type="way" v="Batangas" />
    <tag id="453911758" k="building" o="add" type="way" v="yes" />
    <tag id="453911759" k="Province" o="add" type="way" v="Batangas" />
    <tag id="453911759" k="building" o="add" type="way" v="yes" />
    <tag id="453911760" k="Province" o="add" type="way" v="Batangas" />
    <tag id="453911760" k="building" o="add" type="way" v="yes" />
    <tag id="453911761" k="Province" o="add" type="way" v="Batangas" />
    <tag id="453911761" k="building" o="add" type="way" v="yes" />
    <tag id="453911762" k="Province" o="add" type="way" v="Batangas" />
    <tag id="453911762" k="building" o="add" type="way" v="yes" />
    <tag id="453911763" k="Province" o="add" type="way" v="Batangas" />
    <tag id="453911763" k="building" o="add" type="way" v="yes" />
    <tag id="453911764" k="Province" o="add" type="way" v="Batangas" />
    <tag id="453911764" k="building" o="add" type="way" v="yes" />
    <tag id="453911765" k="Province" o="add" type="way" v="Batangas" />
    <tag id="453911765" k="building" o="add" type="way" v="yes" />
    <tag id="453911766" k="Province" o="add" type="way" v="Batangas" />
    <tag id="453911766" k="building" o="add" type="way" v="yes" />
    <tag id="453911767" k="Province" o="add" type="way" v="Batangas" />
    <tag id="453911767" k="building" o="add" type="way" v="yes" />
    <tag id="453911768" k="Province" o="add" type="way" v="Batangas" />
    <tag id="453911768" k="building" o="add" type="way" v="yes" />
    <tag id="453911769" k="Province" o="add" type="way" v="Batangas" />
    <tag id="453911769" k="building" o="add" type="way" v="yes" />
    <tag id="453911770" k="Province" o="add" type="way" v="Batangas" />
    <tag id="453911770" k="building" o="add" type="way" v="yes" />
    <tag id="453911771" k="Province" o="add" type="way" v="Batangas" />
    <tag id="453911771" k="building" o="add" type="way" v="yes" />
    <tag id="453911772" k="Province" o="add" type="way" v="Batangas" />
    <tag id="453911772" k="building" o="add" type="way" v="yes" />
    <tag id="453911773" k="Province" o="add" type="way" v="Batangas" />
    <tag id="453911773" k="building" o="add" type="way" v="yes" />
    <tag id="453911774" k="Province" o="add" type="way" v="Batangas" />
    <tag id="453911774" k="building" o="add" type="way" v="yes" />
    <tag id="453911775" k="Province" o="add" type="way" v="Batangas" />
    <tag id="453911775" k="building" o="add" type="way" v="yes" />
    <tag id="453911776" k="Province" o="add" type="way" v="Batangas" />
    <tag id="453911776" k="building" o="add" type="way" v="yes" />
    <tag id="453911777" k="Province" o="add" type="way" v="Batangas" />
    <tag id="453911777" k="building" o="add" type="way" v="yes" />
    <tag id="453911778" k="Province" o="add" type="way" v="Batangas" />
    <tag id="453911778" k="building" o="add" type="way" v="yes" />
    <tag id="453911779" k="Province" o="add" type="way" v="Batangas" />
    <tag id="453911779" k="building" o="add" type="way" v="yes" />
    <tag id="453911780" k="Province" o="add" type="way" v="Batangas" />
    <tag id="453911780" k="building" o="add" type="way" v="yes" />
    <tag id="453911781" k="Province" o="add" type="way" v="Batangas" />
    <tag id="453911781" k="building" o="add" type="way" v="yes" />
    <tag id="453911782" k="Province" o="add" type="way" v="Batangas" />
    <tag id="453911782" k="building" o="add" type="way" v="yes" />
    <tag id="453911783" k="Province" o="add" type="way" v="Batangas" />
    <tag id="453911783" k="building" o="add" type="way" v="yes" />
    <tag id="453911784" k="Province" o="add" type="way" v="Batangas" />
    <tag id="453911784" k="building" o="add" type="way" v="yes" />
    <tag id="453911785" k="Province" o="add" type="way" v="Batangas" />
    <tag id="453911785" k="building" o="add" type="way" v="yes" />
    <tag id="453911786" k="Province" o="add" type="way" v="Batangas" />
    <tag id="453911786" k="building" o="add" type="way" v="yes" />
    <tag id="453911787" k="Province" o="add" type="way" v="Batangas" />
    <tag id="453911787" k="building" o="add" type="way" v="yes" />
    <tag id="453911788" k="Province" o="add" type="way" v="Batangas" />
    <tag id="453911788" k="building" o="add" type="way" v="yes" />
    <tag id="453911789" k="Province" o="add" type="way" v="Batangas" />
    <tag id="453911789" k="building" o="add" type="way" v="yes" />
    <tag id="453911790" k="Province" o="add" type="way" v="Batangas" />
    <tag id="453911790" k="building" o="add" type="way" v="yes" />
    <tag id="453911791" k="Province" o="add" type="way" v="Batangas" />
    <tag id="453911791" k="building" o="add" type="way" v="yes" />
    <tag id="453911792" k="Province" o="add" type="way" v="Batangas" />
    <tag id="453911792" k="building" o="add" type="way" v="yes" />
    <tag id="453911793" k="Province" o="add" type="way" v="Batangas" />
    <tag id="453911793" k="building" o="add" type="way" v="yes" />
    <tag id="453911794" k="Province" o="add" type="way" v="Batangas" />
    <tag id="453911794" k="building" o="add" type="way" v="yes" />
    <tag id="453911795" k="Province" o="add" type="way" v="Batangas" />
    <tag id="453911795" k="building" o="add" type="way" v="yes" />
    <tag id="453911796" k="Province" o="add" type="way" v="Batangas" />
    <tag id="453911796" k="building" o="add" type="way" v="yes" />
    <tag id="453911797" k="Province" o="add" type="way" v="Batangas" />
    <tag id="453911797" k="building" o="add" type="way" v="yes" />
    <tag id="453911798" k="Province" o="add" type="way" v="Batangas" />
    <tag id="453911798" k="building" o="add" type="way" v="yes" />
    <tag id="453911799" k="Province" o="add" type="way" v="Batangas" />
    <tag id="453911799" k="building" o="add" type="way" v="yes" />
    <tag id="453911800" k="Province" o="add" type="way" v="Batangas" />
    <tag id="453911800" k="building" o="add" type="way" v="yes" />
    <tag id="453911801" k="Province" o="add" type="way" v="Batangas" />
    <tag id="453911801" k="building" o="add" type="way" v="yes" />
    <tag id="453911802" k="Province" o="add" type="way" v="Batangas" />
    <tag id="453911802" k="building" o="add" type="way" v="yes" />
    <tag id="453911803" k="Province" o="add" type="way" v="Batangas" />
    <tag id="453911803" k="building" o="add" type="way" v="yes" />
    <tag id="453911804" k="Province" o="add" type="way" v="Batangas" />
    <tag id="453911804" k="building" o="add" type="way" v="yes" />
    <tag id="453911805" k="Province" o="add" type="way" v="Batangas" />
    <tag id="453911805" k="building" o="add" type="way" v="yes" />
    <tag id="453911806" k="Province" o="add" type="way" v="Batangas" />
    <tag id="453911806" k="building" o="add" type="way" v="yes" />
    <tag id="453911807" k="Province" o="add" type="way" v="Batangas" />
    <tag id="453911807" k="building" o="add" type="way" v="yes" />
    <tag id="453911808" k="Province" o="add" type="way" v="Batangas" />
    <tag id="453911808" k="building" o="add" type="way" v="yes" />
    <tag id="453911809" k="Province" o="add" type="way" v="Batangas" />
    <tag id="453911809" k="building" o="add" type="way" v="yes" />
    <tag id="453911810" k="Province" o="add" type="way" v="Batangas" />
    <tag id="453911810" k="building" o="add" type="way" v="yes" />
    <tag id="453911811" k="Province" o="add" type="way" v="Batangas" />
    <tag id="453911811" k="building" o="add" type="way" v="yes" />
    <tag id="453911812" k="Province" o="add" type="way" v="Batangas" />
    <tag id="453911812" k="building" o="add" type="way" v="yes" />
    <tag id="453911813" k="Province" o="add" type="way" v="Batangas" />
    <tag id="453911813" k="building" o="add" type="way" v="yes" />
    <tag id="453911814" k="Province" o="add" type="way" v="Batangas" />
    <tag id="453911814" k="building" o="add" type="way" v="yes" />
    <tag id="453911815" k="Province" o="add" type="way" v="Batangas" />
    <tag id="453911815" k="building" o="add" type="way" v="yes" />
    <tag id="453911816" k="Province" o="add" type="way" v="Batangas" />
    <tag id="453911816" k="building" o="add" type="way" v="yes" />
    <tag id="453911817" k="Province" o="add" type="way" v="Batangas" />
    <tag id="453911817" k="building" o="add" type="way" v="yes" />
    <tag id="453911818" k="Province" o="add" type="way" v="Batangas" />
    <tag id="453911818" k="building" o="add" type="way" v="yes" />
    <tag id="453911819" k="Province" o="add" type="way" v="Batangas" />
    <tag id="453911819" k="building" o="add" type="way" v="yes" />
    <tag id="453911820" k="Province" o="add" type="way" v="Batangas" />
    <tag id="453911820" k="building" o="add" type="way" v="yes" />
    <tag id="453911821" k="Province" o="add" type="way" v="Batangas" />
    <tag id="453911821" k="building" o="add" type="way" v="yes" />
    <tag id="453911822" k="Province" o="add" type="way" v="Batangas" />
    <tag id="453911822" k="building" o="add" type="way" v="yes" />
    <tag id="453911823" k="Province" o="add" type="way" v="Batangas" />
    <tag id="453911823" k="building" o="add" type="way" v="yes" />
    <tag id="453911824" k="Province" o="add" type="way" v="Batangas" />
    <tag id="453911824" k="building" o="add" type="way" v="yes" />
    <tag id="453911825" k="Province" o="add" type="way" v="Batangas" />
    <tag id="453911825" k="building" o="add" type="way" v="yes" />
    <tag id="453911826" k="Province" o="add" type="way" v="Batangas" />
    <tag id="453911826" k="building" o="add" type="way" v="yes" />
    <tag id="453911827" k="Province" o="add" type="way" v="Batangas" />
    <tag id="453911827" k="building" o="add" type="way" v="yes" />
    <tag id="453911828" k="Province" o="add" type="way" v="Batangas" />
    <tag id="453911828" k="building" o="add" type="way" v="yes" />
    <tag id="453911829" k="Province" o="add" type="way" v="Batangas" />
    <tag id="453911829" k="building" o="add" type="way" v="yes" />
    <tag id="453911830" k="Province" o="add" type="way" v="Batangas" />
    <tag id="453911830" k="building" o="add" type="way" v="yes" />
    <tag id="453911831" k="Province" o="add" type="way" v="Batangas" />
    <tag id="453911831" k="building" o="add" type="way" v="yes" />
    <tag id="453911832" k="Province" o="add" type="way" v="Batangas" />
    <tag id="453911832" k="building" o="add" type="way" v="yes" />
    <tag id="453911833" k="Province" o="add" type="way" v="Batangas" />
    <tag id="453911833" k="building" o="add" type="way" v="yes" />
    <tag id="453911834" k="Province" o="add" type="way" v="Batangas" />
    <tag id="453911834" k="building" o="add" type="way" v="yes" />
    <tag id="453911835" k="Province" o="add" type="way" v="Batangas" />
    <tag id="453911835" k="building" o="add" type="way" v="yes" />
    <tag id="453911836" k="Province" o="add" type="way" v="Batangas" />
    <tag id="453911836" k="building" o="add" type="way" v="yes" />
    <tag id="453911837" k="Province" o="add" type="way" v="Batangas" />
    <tag id="453911837" k="building" o="add" type="way" v="yes" />
    <tag id="453911838" k="Province" o="add" type="way" v="Batangas" />
    <tag id="453911838" k="building" o="add" type="way" v="yes" />
    <tag id="453911839" k="Province" o="add" type="way" v="Batangas" />
    <tag id="453911839" k="building" o="add" type="way" v="yes" />
    <tag id="453911840" k="Province" o="add" type="way" v="Batangas" />
    <tag id="453911840" k="building" o="add" type="way" v="yes" />
    <tag id="453911841" k="Province" o="add" type="way" v="Batangas" />
    <tag id="453911841" k="building" o="add" type="way" v="yes" />
    <tag id="453911842" k="Province" o="add" type="way" v="Batangas" />
    <tag id="453911842" k="building" o="add" type="way" v="yes" />
    <tag id="453911843" k="Province" o="add" type="way" v="Batangas" />
    <tag id="453911843" k="building" o="add" type="way" v="yes" />
    <tag id="453911844" k="Province" o="add" type="way" v="Batangas" />
    <tag id="453911844" k="building" o="add" type="way" v="yes" />
    <tag id="453911845" k="Province" o="add" type="way" v="Batangas" />
    <tag id="453911845" k="building" o="add" type="way" v="yes" />
    <tag id="453911846" k="Province" o="add" type="way" v="Batangas" />
    <tag id="453911846" k="building" o="add" type="way" v="yes" />
    <tag id="453911847" k="Province" o="add" type="way" v="Batangas" />
    <tag id="453911847" k="building" o="add" type="way" v="yes" />
    <tag id="453911848" k="Province" o="add" type="way" v="Batangas" />
    <tag id="453911848" k="building" o="add" type="way" v="yes" />
    <tag id="453911849" k="Province" o="add" type="way" v="Batangas" />
    <tag id="453911849" k="building" o="add" type="way" v="yes" />
    <tag id="453911850" k="Province" o="add" type="way" v="Batangas" />
    <tag id="453911850" k="building" o="add" type="way" v="yes" />
    <tag id="453911851" k="Province" o="add" type="way" v="Batangas" />
    <tag id="453911851" k="building" o="add" type="way" v="yes" />
    <tag id="453911852" k="Province" o="add" type="way" v="Batangas" />
    <tag id="453911852" k="building" o="add" type="way" v="yes" />
    <tag id="453911853" k="Province" o="add" type="way" v="Batangas" />
    <tag id="453911853" k="building" o="add" type="way" v="yes" />
    <tag id="453911854" k="Province" o="add" type="way" v="Batangas" />
    <tag id="453911854" k="building" o="add" type="way" v="yes" />
    <tag id="453911855" k="Province" o="add" type="way" v="Batangas" />
    <tag id="453911855" k="building" o="add" type="way" v="yes" />
    <tag id="453911856" k="Province" o="add" type="way" v="Batangas" />
    <tag id="453911856" k="building" o="add" type="way" v="yes" />
    <tag id="453911857" k="Province" o="add" type="way" v="Batangas" />
    <tag id="453911857" k="building" o="add" type="way" v="yes" />
    <tag id="453911858" k="Province" o="add" type="way" v="Batangas" />
    <tag id="453911858" k="building" o="add" type="way" v="yes" />
    <tag id="453911859" k="Province" o="add" type="way" v="Batangas" />
    <tag id="453911859" k="building" o="add" type="way" v="yes" />
    <tag id="453911860" k="Province" o="add" type="way" v="Batangas" />
    <tag id="453911860" k="building" o="add" type="way" v="yes" />
    <tag id="453911861" k="Province" o="add" type="way" v="Batangas" />
    <tag id="453911861" k="building" o="add" type="way" v="yes" />
    <tag id="453911863" k="Province" o="add" type="way" v="Batangas" />
    <tag id="453911863" k="building" o="add" type="way" v="yes" />
    <tag id="453911864" k="Province" o="add" type="way" v="Batangas" />
    <tag id="453911864" k="building" o="add" type="way" v="yes" />
    <tag id="453911866" k="Province" o="add" type="way" v="Batangas" />
    <tag id="453911866" k="building" o="add" type="way" v="yes" />
    <tag id="453911867" k="Province" o="add" type="way" v="Batangas" />
    <tag id="453911867" k="building" o="add" type="way" v="yes" />
    <tag id="453911870" k="Province" o="add" type="way" v="Batangas" />
    <tag id="453911870" k="building" o="add" type="way" v="yes" />
    <tag id="453911872" k="Province" o="add" type="way" v="Batangas" />
    <tag id="453911872" k="building" o="add" type="way" v="yes" />
    <tag id="453911874" k="Province" o="add" type="way" v="Batangas" />
    <tag id="453911874" k="building" o="add" type="way" v="yes" />
    <tag id="453911877" k="Province" o="add" type="way" v="Batangas" />
    <tag id="453911877" k="building" o="add" type="way" v="yes" />
    <tag id="453911879" k="Province" o="add" type="way" v="Batangas" />
    <tag id="453911879" k="building" o="add" type="way" v="yes" />
    <tag id="453911881" k="Province" o="add" type="way" v="Batangas" />
    <tag id="453911881" k="building" o="add" type="way" v="yes" />
    <tag id="453911884" k="Province" o="add" type="way" v="Batangas" />
    <tag id="453911884" k="building" o="add" type="way" v="yes" />
    <tag id="453911886" k="Province" o="add" type="way" v="Batangas" />
    <tag id="453911886" k="building" o="add" type="way" v="yes" />
    <tag id="453911888" k="Province" o="add" type="way" v="Batangas" />
    <tag id="453911888" k="building" o="add" type="way" v="yes" />
    <tag id="453911891" k="Province" o="add" type="way" v="Batangas" />
    <tag id="453911891" k="building" o="add" type="way" v="yes" />
    <tag id="453911893" k="Province" o="add" type="way" v="Batangas" />
    <tag id="453911893" k="building" o="add" type="way" v="yes" />
    <tag id="453911895" k="Province" o="add" type="way" v="Batangas" />
    <tag id="453911895" k="building" o="add" type="way" v="yes" />
    <tag id="453911897" k="Province" o="add" type="way" v="Batangas" />
    <tag id="453911897" k="building" o="add" type="way" v="yes" />
    <tag id="453911900" k="Province" o="add" type="way" v="Batangas" />
    <tag id="453911900" k="building" o="add" type="way" v="yes" />
    <tag id="453911901" k="Province" o="add" type="way" v="Batangas" />
    <tag id="453911901" k="building" o="add" type="way" v="yes" />
    <tag id="453911902" k="Province" o="add" type="way" v="Batangas" />
    <tag id="453911902" k="building" o="add" type="way" v="yes" />
    <tag id="453911903" k="Province" o="add" type="way" v="Batangas" />
    <tag id="453911903" k="building" o="add" type="way" v="yes" />
    <tag id="453911904" k="Province" o="add" type="way" v="Batangas" />
    <tag id="453911904" k="building" o="add" type="way" v="yes" />
    <tag id="453911905" k="Province" o="add" type="way" v="Batangas" />
    <tag id="453911905" k="building" o="add" type="way" v="yes" />
    <tag id="453911906" k="Province" o="add" type="way" v="Batangas" />
    <tag id="453911906" k="building" o="add" type="way" v="yes" />
    <tag id="453911907" k="Province" o="add" type="way" v="Batangas" />
    <tag id="453911907" k="building" o="add" type="way" v="yes" />
    <tag id="453911908" k="Province" o="add" type="way" v="Batangas" />
    <tag id="453911908" k="building" o="add" type="way" v="yes" />
    <tag id="453911909" k="Province" o="add" type="way" v="Batangas" />
    <tag id="453911909" k="building" o="add" type="way" v="yes" />
    <tag id="453911910" k="Province" o="add" type="way" v="Batangas" />
    <tag id="453911910" k="building" o="add" type="way" v="yes" />
    <tag id="453911911" k="Province" o="add" type="way" v="Batangas" />
    <tag id="453911911" k="building" o="add" type="way" v="yes" />
    <tag id="453911912" k="Province" o="add" type="way" v="Batangas" />
    <tag id="453911912" k="building" o="add" type="way" v="yes" />
    <tag id="453911913" k="Province" o="add" type="way" v="Batangas" />
    <tag id="453911913" k="building" o="add" type="way" v="yes" />
    <tag id="453911914" k="Province" o="add" type="way" v="Batangas" />
    <tag id="453911914" k="building" o="add" type="way" v="yes" />
    <tag id="453911915" k="Province" o="add" type="way" v="Batangas" />
    <tag id="453911915" k="building" o="add" type="way" v="yes" />
    <tag id="453911916" k="Province" o="add" type="way" v="Batangas" />
    <tag id="453911916" k="building" o="add" type="way" v="yes" />
    <tag id="453911917" k="Province" o="add" type="way" v="Batangas" />
    <tag id="453911917" k="building" o="add" type="way" v="yes" />
    <tag id="453911918" k="Province" o="add" type="way" v="Batangas" />
    <tag id="453911918" k="building" o="add" type="way" v="yes" />
    <tag id="453911919" k="Province" o="add" type="way" v="Batangas" />
    <tag id="453911919" k="building" o="add" type="way" v="yes" />
    <tag id="453911920" k="Province" o="add" type="way" v="Batangas" />
    <tag id="453911920" k="building" o="add" type="way" v="yes" />
    <tag id="453911921" k="Province" o="add" type="way" v="Batangas" />
    <tag id="453911921" k="building" o="add" type="way" v="yes" />
    <tag id="453911922" k="Province" o="add" type="way" v="Batangas" />
    <tag id="453911922" k="building" o="add" type="way" v="yes" />
    <tag id="453911923" k="Province" o="add" type="way" v="Batangas" />
    <tag id="453911923" k="building" o="add" type="way" v="yes" />
    <tag id="453911924" k="Province" o="add" type="way" v="Batangas" />
    <tag id="453911924" k="building" o="add" type="way" v="yes" />
    <tag id="453911925" k="Province" o="add" type="way" v="Batangas" />
    <tag id="453911925" k="building" o="add" type="way" v="yes" />
    <tag id="453911926" k="Province" o="add" type="way" v="Batangas" />
    <tag id="453911926" k="building" o="add" type="way" v="yes" />
    <tag id="453911927" k="Province" o="add" type="way" v="Batangas" />
    <tag id="453911927" k="building" o="add" type="way" v="yes" />
    <tag id="453911928" k="Province" o="add" type="way" v="Batangas" />
    <tag id="453911928" k="building" o="add" type="way" v="yes" />
    <tag id="453911929" k="Province" o="add" type="way" v="Batangas" />
    <tag id="453911929" k="building" o="add" type="way" v="yes" />
    <tag id="453911930" k="Province" o="add" type="way" v="Batangas" />
    <tag id="453911930" k="building" o="add" type="way" v="yes" />
    <tag id="453911931" k="Province" o="add" type="way" v="Batangas" />
    <tag id="453911931" k="building" o="add" type="way" v="yes" />
    <tag id="453911932" k="Province" o="add" type="way" v="Batangas" />
    <tag id="453911932" k="building" o="add" type="way" v="yes" />
    <tag id="453911933" k="Province" o="add" type="way" v="Batangas" />
    <tag id="453911933" k="building" o="add" type="way" v="yes" />
    <tag id="453911934" k="Province" o="add" type="way" v="Batangas" />
    <tag id="453911934" k="building" o="add" type="way" v="yes" />
    <tag id="453911935" k="Province" o="add" type="way" v="Batangas" />
    <tag id="453911935" k="building" o="add" type="way" v="yes" />
    <tag id="453911936" k="Province" o="add" type="way" v="Batangas" />
    <tag id="453911936" k="building" o="add" type="way" v="yes" />
    <tag id="453911937" k="Province" o="add" type="way" v="Batangas" />
    <tag id="453911937" k="building" o="add" type="way" v="yes" />
    <tag id="453911938" k="Province" o="add" type="way" v="Batangas" />
    <tag id="453911938" k="building" o="add" type="way" v="yes" />
    <tag id="453911939" k="Province" o="add" type="way" v="Batangas" />
    <tag id="453911939" k="building" o="add" type="way" v="yes" />
    <tag id="453911940" k="Province" o="add" type="way" v="Batangas" />
    <tag id="453911940" k="building" o="add" type="way" v="yes" />
    <tag id="453911941" k="Province" o="add" type="way" v="Batangas" />
    <tag id="453911941" k="building" o="add" type="way" v="yes" />
    <tag id="453911942" k="Province" o="add" type="way" v="Batangas" />
    <tag id="453911942" k="building" o="add" type="way" v="yes" />
    <tag id="453911943" k="Province" o="add" type="way" v="Batangas" />
    <tag id="453911943" k="building" o="add" type="way" v="yes" />
    <tag id="453911944" k="Province" o="add" type="way" v="Batangas" />
    <tag id="453911944" k="building" o="add" type="way" v="yes" />
    <tag id="453911945" k="Province" o="add" type="way" v="Batangas" />
    <tag id="453911945" k="building" o="add" type="way" v="yes" />
    <tag id="453911946" k="Province" o="add" type="way" v="Batangas" />
    <tag id="453911946" k="building" o="add" type="way" v="yes" />
    <tag id="453911947" k="Province" o="add" type="way" v="Batangas" />
    <tag id="453911947" k="building" o="add" type="way" v="yes" />
    <tag id="453911948" k="Province" o="add" type="way" v="Batangas" />
    <tag id="453911948" k="building" o="add" type="way" v="yes" />
    <tag id="453911949" k="Province" o="add" type="way" v="Batangas" />
    <tag id="453911949" k="building" o="add" type="way" v="yes" />
    <tag id="453911950" k="Province" o="add" type="way" v="Batangas" />
    <tag id="453911950" k="building" o="add" type="way" v="yes" />
    <tag id="453911951" k="Province" o="add" type="way" v="Batangas" />
    <tag id="453911951" k="building" o="add" type="way" v="yes" />
    <tag id="453911952" k="Province" o="add" type="way" v="Batangas" />
    <tag id="453911952" k="building" o="add" type="way" v="yes" />
    <tag id="453911953" k="Province" o="add" type="way" v="Batangas" />
    <tag id="453911953" k="building" o="add" type="way" v="yes" />
    <tag id="453911954" k="Province" o="add" type="way" v="Batangas" />
    <tag id="453911954" k="building" o="add" type="way" v="yes" />
    <tag id="453911955" k="Province" o="add" type="way" v="Batangas" />
    <tag id="453911955" k="building" o="add" type="way" v="yes" />
    <tag id="453911956" k="Province" o="add" type="way" v="Batangas" />
    <tag id="453911956" k="building" o="add" type="way" v="yes" />
    <tag id="453911957" k="Province" o="add" type="way" v="Batangas" />
    <tag id="453911957" k="building" o="add" type="way" v="yes" />
    <tag id="453911958" k="Province" o="add" type="way" v="Batangas" />
    <tag id="453911958" k="building" o="add" type="way" v="yes" />
    <tag id="453911959" k="Province" o="add" type="way" v="Batangas" />
    <tag id="453911959" k="building" o="add" type="way" v="yes" />
    <tag id="453911960" k="Province" o="add" type="way" v="Batangas" />
    <tag id="453911960" k="building" o="add" type="way" v="yes" />
    <tag id="453911961" k="Province" o="add" type="way" v="Batangas" />
    <tag id="453911961" k="building" o="add" type="way" v="yes" />
    <tag id="453911962" k="Province" o="add" type="way" v="Batangas" />
    <tag id="453911962" k="building" o="add" type="way" v="yes" />
    <tag id="453911963" k="Province" o="add" type="way" v="Batangas" />
    <tag id="453911963" k="building" o="add" type="way" v="yes" />
    <tag id="453911964" k="Province" o="add" type="way" v="Batangas" />
    <tag id="453911964" k="building" o="add" type="way" v="yes" />
    <tag id="453911965" k="Province" o="add" type="way" v="Batangas" />
    <tag id="453911965" k="building" o="add" type="way" v="yes" />
    <tag id="453911966" k="Province" o="add" type="way" v="Batangas" />
    <tag id="453911966" k="building" o="add" type="way" v="yes" />
    <tag id="453911967" k="Province" o="add" type="way" v="Batangas" />
    <tag id="453911967" k="building" o="add" type="way" v="yes" />
    <tag id="453911968" k="Province" o="add" type="way" v="Batangas" />
    <tag id="453911968" k="building" o="add" type="way" v="yes" />
    <tag id="453911969" k="Province" o="add" type="way" v="Batangas" />
    <tag id="453911969" k="building" o="add" type="way" v="yes" />
    <tag id="453911970" k="Province" o="add" type="way" v="Batangas" />
    <tag id="453911970" k="building" o="add" type="way" v="yes" />
    <tag id="453911971" k="Province" o="add" type="way" v="Batangas" />
    <tag id="453911971" k="building" o="add" type="way" v="yes" />
    <tag id="453911972" k="Province" o="add" type="way" v="Batangas" />
    <tag id="453911972" k="building" o="add" type="way" v="yes" />
    <tag id="453911973" k="Province" o="add" type="way" v="Batangas" />
    <tag id="453911973" k="building" o="add" type="way" v="yes" />
    <tag id="453911974" k="Province" o="add" type="way" v="Batangas" />
    <tag id="453911974" k="building" o="add" type="way" v="yes" />
    <tag id="453911975" k="Province" o="add" type="way" v="Batangas" />
    <tag id="453911975" k="building" o="add" type="way" v="yes" />
    <tag id="453911976" k="Province" o="add" type="way" v="Batangas" />
    <tag id="453911976" k="building" o="add" type="way" v="yes" />
    <tag id="453911977" k="Province" o="add" type="way" v="Batangas" />
    <tag id="453911977" k="building" o="add" type="way" v="yes" />
    <tag id="453911978" k="Province" o="add" type="way" v="Batangas" />
    <tag id="453911978" k="building" o="add" type="way" v="yes" />
    <tag id="453911979" k="Province" o="add" type="way" v="Batangas" />
    <tag id="453911979" k="building" o="add" type="way" v="yes" />
    <tag id="453911980" k="Province" o="add" type="way" v="Batangas" />
    <tag id="453911980" k="building" o="add" type="way" v="yes" />
    <tag id="453911981" k="Province" o="add" type="way" v="Batangas" />
    <tag id="453911981" k="building" o="add" type="way" v="yes" />
    <tag id="453911982" k="Province" o="add" type="way" v="Batangas" />
    <tag id="453911982" k="building" o="add" type="way" v="yes" />
    <tag id="453911983" k="Province" o="add" type="way" v="Batangas" />
    <tag id="453911983" k="building" o="add" type="way" v="yes" />
    <tag id="453911984" k="Province" o="add" type="way" v="Batangas" />
    <tag id="453911984" k="building" o="add" type="way" v="yes" />
    <tag id="453911985" k="Province" o="add" type="way" v="Batangas" />
    <tag id="453911985" k="building" o="add" type="way" v="yes" />
    <tag id="453911986" k="Province" o="add" type="way" v="Batangas" />
    <tag id="453911986" k="building" o="add" type="way" v="yes" />
    <tag id="453911987" k="Province" o="add" type="way" v="Batangas" />
    <tag id="453911987" k="building" o="add" type="way" v="yes" />
    <tag id="453911988" k="Province" o="add" type="way" v="Batangas" />
    <tag id="453911988" k="building" o="add" type="way" v="yes" />
    <tag id="453911989" k="Province" o="add" type="way" v="Batangas" />
    <tag id="453911989" k="building" o="add" type="way" v="yes" />
    <tag id="453911990" k="Province" o="add" type="way" v="Batangas" />
    <tag id="453911990" k="building" o="add" type="way" v="yes" />
    <tag id="453911991" k="Province" o="add" type="way" v="Batangas" />
    <tag id="453911991" k="building" o="add" type="way" v="yes" />
    <tag id="453911992" k="Province" o="add" type="way" v="Batangas" />
    <tag id="453911992" k="building" o="add" type="way" v="yes" />
    <tag id="453911993" k="Province" o="add" type="way" v="Batangas" />
    <tag id="453911993" k="building" o="add" type="way" v="yes" />
    <tag id="453911994" k="Province" o="add" type="way" v="Batangas" />
    <tag id="453911994" k="building" o="add" type="way" v="yes" />
    <tag id="453911995" k="Province" o="add" type="way" v="Batangas" />
    <tag id="453911995" k="building" o="add" type="way" v="yes" />
    <tag id="453911996" k="Province" o="add" type="way" v="Batangas" />
    <tag id="453911996" k="building" o="add" type="way" v="yes" />
    <tag id="453911997" k="Province" o="add" type="way" v="Batangas" />
    <tag id="453911997" k="building" o="add" type="way" v="yes" />
    <tag id="453911998" k="Province" o="add" type="way" v="Batangas" />
    <tag id="453911998" k="building" o="add" type="way" v="yes" />
    <tag id="453911999" k="Province" o="add" type="way" v="Batangas" />
    <tag id="453911999" k="building" o="add" type="way" v="yes" />
    <tag id="453912000" k="Province" o="add" type="way" v="Batangas" />
    <tag id="453912000" k="building" o="add" type="way" v="yes" />
    <tag id="453912001" k="Province" o="add" type="way" v="Batangas" />
    <tag id="453912001" k="building" o="add" type="way" v="yes" />
    <tag id="453912002" k="Province" o="add" type="way" v="Batangas" />
    <tag id="453912002" k="building" o="add" type="way" v="yes" />
    <tag id="453912005" k="Province" o="add" type="way" v="Batangas" />
    <tag id="453912005" k="building" o="add" type="way" v="yes" />
    <tag id="453912006" k="Province" o="add" type="way" v="Batangas" />
    <tag id="453912006" k="building" o="add" type="way" v="yes" />
    <tag id="453912008" k="Province" o="add" type="way" v="Batangas" />
    <tag id="453912008" k="building" o="add" type="way" v="yes" />
    <tag id="453912010" k="Province" o="add" type="way" v="Batangas" />
    <tag id="453912010" k="building" o="add" type="way" v="yes" />
    <tag id="453912012" k="Province" o="add" type="way" v="Batangas" />
    <tag id="453912012" k="building" o="add" type="way" v="yes" />
    <tag id="453912013" k="Province" o="add" type="way" v="Batangas" />
    <tag id="453912013" k="building" o="add" type="way" v="yes" />
    <tag id="453912014" k="Province" o="add" type="way" v="Batangas" />
    <tag id="453912014" k="building" o="add" type="way" v="yes" />
    <tag id="453912015" k="Province" o="add" type="way" v="Batangas" />
    <tag id="453912015" k="building" o="add" type="way" v="yes" />
    <tag id="453912016" k="Province" o="add" type="way" v="Batangas" />
    <tag id="453912016" k="building" o="add" type="way" v="yes" />
    <tag id="453912017" k="Province" o="add" type="way" v="Batangas" />
    <tag id="453912017" k="building" o="add" type="way" v="yes" />
    <tag id="453912018" k="Province" o="add" type="way" v="Batangas" />
    <tag id="453912018" k="building" o="add" type="way" v="yes" />
    <tag id="453912019" k="Province" o="add" type="way" v="Batangas" />
    <tag id="453912019" k="building" o="add" type="way" v="yes" />
    <tag id="453912020" k="Province" o="add" type="way" v="Batangas" />
    <tag id="453912020" k="building" o="add" type="way" v="yes" />
    <tag id="453912021" k="Province" o="add" type="way" v="Batangas" />
    <tag id="453912021" k="building" o="add" type="way" v="yes" />
    <tag id="453912022" k="Province" o="add" type="way" v="Batangas" />
    <tag id="453912022" k="building" o="add" type="way" v="yes" />
    <tag id="453912023" k="Province" o="add" type="way" v="Batangas" />
    <tag id="453912023" k="building" o="add" type="way" v="yes" />
    <tag id="453912024" k="Province" o="add" type="way" v="Batangas" />
    <tag id="453912024" k="building" o="add" type="way" v="yes" />
    <tag id="453912025" k="Province" o="add" type="way" v="Batangas" />
    <tag id="453912025" k="building" o="add" type="way" v="yes" />
    <tag id="453912026" k="Province" o="add" type="way" v="Batangas" />
    <tag id="453912026" k="building" o="add" type="way" v="yes" />
    <tag id="453912027" k="Province" o="add" type="way" v="Batangas" />
    <tag id="453912027" k="building" o="add" type="way" v="yes" />
    <tag id="453912028" k="Province" o="add" type="way" v="Batangas" />
    <tag id="453912028" k="building" o="add" type="way" v="yes" />
    <tag id="453912029" k="Province" o="add" type="way" v="Batangas" />
    <tag id="453912029" k="building" o="add" type="way" v="yes" />
    <tag id="453912030" k="Province" o="add" type="way" v="Batangas" />
    <tag id="453912030" k="building" o="add" type="way" v="yes" />
    <tag id="453912031" k="Province" o="add" type="way" v="Batangas" />
    <tag id="453912031" k="building" o="add" type="way" v="yes" />
    <tag id="453912032" k="Province" o="add" type="way" v="Batangas" />
    <tag id="453912032" k="building" o="add" type="way" v="yes" />
    <tag id="453912033" k="Province" o="add" type="way" v="Batangas" />
    <tag id="453912033" k="building" o="add" type="way" v="yes" />
    <tag id="453912034" k="Province" o="add" type="way" v="Batangas" />
    <tag id="453912034" k="building" o="add" type="way" v="yes" />
    <tag id="453912035" k="Province" o="add" type="way" v="Batangas" />
    <tag id="453912035" k="building" o="add" type="way" v="yes" />
    <tag id="453912036" k="Province" o="add" type="way" v="Batangas" />
    <tag id="453912036" k="building" o="add" type="way" v="yes" />
    <tag id="453912037" k="Province" o="add" type="way" v="Batangas" />
    <tag id="453912037" k="building" o="add" type="way" v="yes" />
    <tag id="453912038" k="Province" o="add" type="way" v="Batangas" />
    <tag id="453912038" k="building" o="add" type="way" v="yes" />
    <tag id="453912039" k="Province" o="add" type="way" v="Batangas" />
    <tag id="453912039" k="building" o="add" type="way" v="yes" />
    <tag id="453912040" k="Province" o="add" type="way" v="Batangas" />
    <tag id="453912040" k="building" o="add" type="way" v="yes" />
    <tag id="453912041" k="Province" o="add" type="way" v="Batangas" />
    <tag id="453912041" k="building" o="add" type="way" v="yes" />
    <tag id="453912042" k="Province" o="add" type="way" v="Batangas" />
    <tag id="453912042" k="building" o="add" type="way" v="yes" />
    <tag id="453912043" k="Province" o="add" type="way" v="Batangas" />
    <tag id="453912043" k="building" o="add" type="way" v="yes" />
    <tag id="453912044" k="Province" o="add" type="way" v="Batangas" />
    <tag id="453912044" k="building" o="add" type="way" v="yes" />
    <tag id="453912045" k="Province" o="add" type="way" v="Batangas" />
    <tag id="453912045" k="building" o="add" type="way" v="yes" />
    <tag id="453912046" k="Province" o="add" type="way" v="Batangas" />
    <tag id="453912046" k="building" o="add" type="way" v="yes" />
    <tag id="453912047" k="Province" o="add" type="way" v="Batangas" />
    <tag id="453912047" k="building" o="add" type="way" v="yes" />
    <tag id="453912048" k="Province" o="add" type="way" v="Batangas" />
    <tag id="453912048" k="building" o="add" type="way" v="yes" />
    <tag id="453912049" k="Province" o="add" type="way" v="Batangas" />
    <tag id="453912049" k="building" o="add" type="way" v="yes" />
    <tag id="453912050" k="Province" o="add" type="way" v="Batangas" />
    <tag id="453912050" k="building" o="add" type="way" v="yes" />
    <tag id="453912051" k="Province" o="add" type="way" v="Batangas" />
    <tag id="453912051" k="building" o="add" type="way" v="yes" />
    <tag id="453912052" k="Province" o="add" type="way" v="Batangas" />
    <tag id="453912052" k="building" o="add" type="way" v="yes" />
    <tag id="453912053" k="Province" o="add" type="way" v="Batangas" />
    <tag id="453912053" k="building" o="add" type="way" v="yes" />
    <tag id="453912054" k="Province" o="add" type="way" v="Batangas" />
    <tag id="453912054" k="building" o="add" type="way" v="yes" />
    <tag id="453912055" k="Province" o="add" type="way" v="Batangas" />
    <tag id="453912055" k="building" o="add" type="way" v="yes" />
    <tag id="453912056" k="Province" o="add" type="way" v="Batangas" />
    <tag id="453912056" k="building" o="add" type="way" v="yes" />
    <tag id="453912057" k="Province" o="add" type="way" v="Batangas" />
    <tag id="453912057" k="building" o="add" type="way" v="yes" />
    <tag id="453912058" k="Province" o="add" type="way" v="Batangas" />
    <tag id="453912058" k="building" o="add" type="way" v="yes" />
    <tag id="453912059" k="Province" o="add" type="way" v="Batangas" />
    <tag id="453912059" k="building" o="add" type="way" v="yes" />
    <tag id="453912060" k="Province" o="add" type="way" v="Batangas" />
    <tag id="453912060" k="building" o="add" type="way" v="yes" />
    <tag id="453912061" k="Province" o="add" type="way" v="Batangas" />
    <tag id="453912061" k="building" o="add" type="way" v="yes" />
    <tag id="453912062" k="Province" o="add" type="way" v="Batangas" />
    <tag id="453912062" k="building" o="add" type="way" v="yes" />
    <tag id="453912063" k="Province" o="add" type="way" v="Batangas" />
    <tag id="453912063" k="building" o="add" type="way" v="yes" />
    <tag id="453912064" k="Province" o="add" type="way" v="Batangas" />
    <tag id="453912064" k="building" o="add" type="way" v="yes" />
    <tag id="453912065" k="Province" o="add" type="way" v="Batangas" />
    <tag id="453912065" k="building" o="add" type="way" v="yes" />
    <tag id="453912066" k="Province" o="add" type="way" v="Batangas" />
    <tag id="453912066" k="building" o="add" type="way" v="yes" />
    <tag id="453912067" k="Province" o="add" type="way" v="Batangas" />
    <tag id="453912067" k="building" o="add" type="way" v="yes" />
    <tag id="453912068" k="Province" o="add" type="way" v="Batangas" />
    <tag id="453912068" k="building" o="add" type="way" v="yes" />
    <tag id="453912069" k="Province" o="add" type="way" v="Batangas" />
    <tag id="453912069" k="building" o="add" type="way" v="yes" />
    <tag id="453912070" k="Province" o="add" type="way" v="Batangas" />
    <tag id="453912070" k="building" o="add" type="way" v="yes" />
    <tag id="453912071" k="Province" o="add" type="way" v="Batangas" />
    <tag id="453912071" k="building" o="add" type="way" v="yes" />
    <tag id="453912072" k="Province" o="add" type="way" v="Batangas" />
    <tag id="453912072" k="building" o="add" type="way" v="yes" />
    <tag id="453912073" k="Province" o="add" type="way" v="Batangas" />
    <tag id="453912073" k="building" o="add" type="way" v="yes" />
    <tag id="453912074" k="Province" o="add" type="way" v="Batangas" />
    <tag id="453912074" k="building" o="add" type="way" v="yes" />
    <tag id="453912075" k="Province" o="add" type="way" v="Batangas" />
    <tag id="453912075" k="building" o="add" type="way" v="yes" />
    <tag id="453912076" k="Province" o="add" type="way" v="Batangas" />
    <tag id="453912076" k="building" o="add" type="way" v="yes" />
    <tag id="453912077" k="Province" o="add" type="way" v="Batangas" />
    <tag id="453912077" k="building" o="add" type="way" v="yes" />
    <tag id="453912078" k="Province" o="add" type="way" v="Batangas" />
    <tag id="453912078" k="building" o="add" type="way" v="yes" />
    <tag id="453912079" k="Province" o="add" type="way" v="Batangas" />
    <tag id="453912079" k="building" o="add" type="way" v="yes" />
    <tag id="453912080" k="Province" o="add" type="way" v="Batangas" />
    <tag id="453912080" k="building" o="add" type="way" v="yes" />
    <tag id="453912081" k="Province" o="add" type="way" v="Batangas" />
    <tag id="453912081" k="building" o="add" type="way" v="yes" />
    <tag id="453912082" k="Province" o="add" type="way" v="Batangas" />
    <tag id="453912082" k="building" o="add" type="way" v="yes" />
    <tag id="453912083" k="Province" o="add" type="way" v="Batangas" />
    <tag id="453912083" k="building" o="add" type="way" v="yes" />
    <tag id="453912084" k="Province" o="add" type="way" v="Batangas" />
    <tag id="453912084" k="building" o="add" type="way" v="yes" />
    <tag id="453912085" k="Province" o="add" type="way" v="Batangas" />
    <tag id="453912085" k="building" o="add" type="way" v="yes" />
    <tag id="453912086" k="Province" o="add" type="way" v="Batangas" />
    <tag id="453912086" k="building" o="add" type="way" v="yes" />
    <tag id="453912087" k="Province" o="add" type="way" v="Batangas" />
    <tag id="453912087" k="building" o="add" type="way" v="yes" />
    <tag id="453912088" k="Province" o="add" type="way" v="Batangas" />
    <tag id="453912088" k="building" o="add" type="way" v="yes" />
    <tag id="453912089" k="Province" o="add" type="way" v="Batangas" />
    <tag id="453912089" k="building" o="add" type="way" v="yes" />
    <tag id="453912090" k="Province" o="add" type="way" v="Batangas" />
    <tag id="453912090" k="building" o="add" type="way" v="yes" />
    <tag id="453912091" k="Province" o="add" type="way" v="Batangas" />
    <tag id="453912091" k="building" o="add" type="way" v="yes" />
    <tag id="453912092" k="Province" o="add" type="way" v="Batangas" />
    <tag id="453912092" k="building" o="add" type="way" v="yes" />
    <tag id="453912094" k="Province" o="add" type="way" v="Batangas" />
    <tag id="453912094" k="building" o="add" type="way" v="yes" />
    <tag id="453912095" k="Province" o="add" type="way" v="Batangas" />
    <tag id="453912095" k="building" o="add" type="way" v="yes" />
    <tag id="453912096" k="Province" o="add" type="way" v="Batangas" />
    <tag id="453912096" k="building" o="add" type="way" v="yes" />
    <tag id="453912097" k="Province" o="add" type="way" v="Batangas" />
    <tag id="453912097" k="building" o="add" type="way" v="yes" />
    <tag id="453912098" k="Province" o="add" type="way" v="Batangas" />
    <tag id="453912098" k="building" o="add" type="way" v="yes" />
    <tag id="453912099" k="Province" o="add" type="way" v="Batangas" />
    <tag id="453912099" k="building" o="add" type="way" v="yes" />
    <tag id="453912100" k="Province" o="add" type="way" v="Batangas" />
    <tag id="453912100" k="building" o="add" type="way" v="yes" />
    <tag id="453912101" k="Province" o="add" type="way" v="Batangas" />
    <tag id="453912101" k="building" o="add" type="way" v="yes" />
    <tag id="453912102" k="Province" o="add" type="way" v="Batangas" />
    <tag id="453912102" k="building" o="add" type="way" v="yes" />
    <tag id="453912103" k="Province" o="add" type="way" v="Batangas" />
    <tag id="453912103" k="building" o="add" type="way" v="yes" />
    <tag id="453912104" k="Province" o="add" type="way" v="Batangas" />
    <tag id="453912104" k="building" o="add" type="way" v="yes" />
    <tag id="453912105" k="Province" o="add" type="way" v="Batangas" />
    <tag id="453912105" k="building" o="add" type="way" v="yes" />
    <tag id="453912106" k="Province" o="add" type="way" v="Batangas" />
    <tag id="453912106" k="building" o="add" type="way" v="yes" />
    <tag id="453912107" k="Province" o="add" type="way" v="Batangas" />
    <tag id="453912107" k="building" o="add" type="way" v="yes" />
    <tag id="453912108" k="Province" o="add" type="way" v="Batangas" />
    <tag id="453912108" k="building" o="add" type="way" v="yes" />
    <tag id="453912109" k="Province" o="add" type="way" v="Batangas" />
    <tag id="453912109" k="building" o="add" type="way" v="yes" />
    <tag id="453912110" k="Province" o="add" type="way" v="Batangas" />
    <tag id="453912110" k="building" o="add" type="way" v="yes" />
    <tag id="453912111" k="Province" o="add" type="way" v="Batangas" />
    <tag id="453912111" k="building" o="add" type="way" v="yes" />
    <tag id="453912112" k="Province" o="add" type="way" v="Batangas" />
    <tag id="453912112" k="building" o="add" type="way" v="yes" />
    <tag id="453912113" k="Province" o="add" type="way" v="Batangas" />
    <tag id="453912113" k="building" o="add" type="way" v="yes" />
    <tag id="453912114" k="Province" o="add" type="way" v="Batangas" />
    <tag id="453912114" k="building" o="add" type="way" v="yes" />
    <tag id="453912115" k="Province" o="add" type="way" v="Batangas" />
    <tag id="453912115" k="building" o="add" type="way" v="yes" />
    <tag id="453912116" k="Province" o="add" type="way" v="Batangas" />
    <tag id="453912116" k="building" o="add" type="way" v="yes" />
    <tag id="453912117" k="Province" o="add" type="way" v="Batangas" />
    <tag id="453912117" k="building" o="add" type="way" v="yes" />
    <tag id="453912118" k="Province" o="add" type="way" v="Batangas" />
    <tag id="453912118" k="building" o="add" type="way" v="yes" />
    <tag id="453912119" k="Province" o="add" type="way" v="Batangas" />
    <tag id="453912119" k="building" o="add" type="way" v="yes" />
    <tag id="453912120" k="Province" o="add" type="way" v="Batangas" />
    <tag id="453912120" k="building" o="add" type="way" v="yes" />
    <tag id="453912121" k="Province" o="add" type="way" v="Batangas" />
    <tag id="453912121" k="building" o="add" type="way" v="yes" />
    <tag id="453912122" k="Province" o="add" type="way" v="Batangas" />
    <tag id="453912122" k="building" o="add" type="way" v="yes" />
    <tag id="453912123" k="Province" o="add" type="way" v="Batangas" />
    <tag id="453912123" k="building" o="add" type="way" v="yes" />
    <tag id="453912125" k="Province" o="add" type="way" v="Batangas" />
    <tag id="453912125" k="building" o="add" type="way" v="yes" />
    <tag id="453912127" k="Province" o="add" type="way" v="Batangas" />
    <tag id="453912127" k="building" o="add" type="way" v="yes" />
    <tag id="453912129" k="Province" o="add" type="way" v="Batangas" />
    <tag id="453912129" k="building" o="add" type="way" v="yes" />
    <tag id="453912130" k="Province" o="add" type="way" v="Batangas" />
    <tag id="453912130" k="building" o="add" type="way" v="yes" />
    <tag id="453912131" k="Province" o="add" type="way" v="Batangas" />
    <tag id="453912131" k="building" o="add" type="way" v="yes" />
    <tag id="453912132" k="Province" o="add" type="way" v="Batangas" />
    <tag id="453912132" k="building" o="add" type="way" v="yes" />
    <tag id="453912133" k="Province" o="add" type="way" v="Batangas" />
    <tag id="453912133" k="building" o="add" type="way" v="yes" />
    <tag id="453912134" k="Province" o="add" type="way" v="Batangas" />
    <tag id="453912134" k="building" o="add" type="way" v="yes" />
    <tag id="453912135" k="Province" o="add" type="way" v="Batangas" />
    <tag id="453912135" k="building" o="add" type="way" v="yes" />
    <tag id="453912136" k="Province" o="add" type="way" v="Batangas" />
    <tag id="453912136" k="building" o="add" type="way" v="yes" />
    <tag id="453912137" k="Province" o="add" type="way" v="Batangas" />
    <tag id="453912137" k="building" o="add" type="way" v="yes" />
    <tag id="453912138" k="Province" o="add" type="way" v="Batangas" />
    <tag id="453912138" k="building" o="add" type="way" v="yes" />
    <tag id="453912139" k="Province" o="add" type="way" v="Batangas" />
    <tag id="453912139" k="building" o="add" type="way" v="yes" />
    <tag id="453912140" k="Province" o="add" type="way" v="Batangas" />
    <tag id="453912140" k="building" o="add" type="way" v="yes" />
    <tag id="453912141" k="Province" o="add" type="way" v="Batangas" />
    <tag id="453912141" k="building" o="add" type="way" v="yes" />
    <tag id="453912142" k="Province" o="add" type="way" v="Batangas" />
    <tag id="453912142" k="building" o="add" type="way" v="yes" />
    <tag id="453912143" k="Province" o="add" type="way" v="Batangas" />
    <tag id="453912143" k="building" o="add" type="way" v="yes" />
    <tag id="453912144" k="Province" o="add" type="way" v="Batangas" />
    <tag id="453912144" k="building" o="add" type="way" v="yes" />
    <tag id="453912145" k="Province" o="add" type="way" v="Batangas" />
    <tag id="453912145" k="building" o="add" type="way" v="yes" />
    <tag id="453912146" k="Province" o="add" type="way" v="Batangas" />
    <tag id="453912146" k="building" o="add" type="way" v="yes" />
    <tag id="453912147" k="Province" o="add" type="way" v="Batangas" />
    <tag id="453912147" k="building" o="add" type="way" v="yes" />
    <tag id="453912148" k="Province" o="add" type="way" v="Batangas" />
    <tag id="453912148" k="building" o="add" type="way" v="yes" />
    <tag id="453912149" k="Province" o="add" type="way" v="Batangas" />
    <tag id="453912149" k="building" o="add" type="way" v="yes" />
  </body>
</changeset>
